ordering/__init__.py
ordering/utils.py
ordering-0.1.0.dist-info/DESCRIPTION.rst
ordering-0.1.0.dist-info/METADATA
ordering-0.1.0.dist-info/RECORD
ordering-0.1.0.dist-info/WHEEL
ordering-0.1.0.dist-info/metadata.json
ordering-0.1.0.dist-info/top_level.txt
