Metadata-Version: 2.0
Name: ordering
Version: 0.1.0
Summary: A data structure to impose a total order on a collection of objects
Home-page: https://github.com/madman-bob/python-order-maintenance
Author: Robert Wright
Author-email: madman.bob@hotmail.co.uk
License: MIT
Keywords: order,ordering
Platform: UNKNOWN
Classifier: Development Status :: 3 - Alpha
Classifier: Intended Audience :: Developers
Classifier: License :: OSI Approved :: MIT License
Classifier: Programming Language :: Python :: 3
Classifier: Programming Language :: Python :: 3.6
Requires-Python: >=3.6
